crypto_fernet/__init__.py
crypto_fernet/__main__.py
crypto_fernet/crypto_fernet.py
crypto_fernet-0.1.0.dist-info/AUTHORS.rst
crypto_fernet-0.1.0.dist-info/LICENSE
crypto_fernet-0.1.0.dist-info/METADATA
crypto_fernet-0.1.0.dist-info/WHEEL
crypto_fernet-0.1.0.dist-info/entry_points.txt
crypto_fernet-0.1.0.dist-info/top_level.txt
crypto_fernet-0.1.0.dist-info/RECORD
