Metadata-Version: 1.2
Name: crypto-fernet
Version: 0.1.0
Summary: CLI tool for symmetric encryption/decryption using cryptography.fernet
Home-page: https://github.com/sergray/crypto_fernet
Author: Sergey Panfilov
Author-email: sergray@gmail.com
License: MIT license
Keywords: crypto_fernet
Platform: UNKNOWN
Classifier: Development Status :: 2 - Pre-Alpha
Classifier: Intended Audience :: Developers
Classifier: License :: OSI Approved :: MIT License
Classifier: Natural Language :: English
Classifier: Programming Language :: Python :: 3
Classifier: Programming Language :: Python :: 3.7
Classifier: Programming Language :: Python :: 3.8
Classifier: Programming Language :: Python :: 3.9
Requires-Python: >=3.7
